qm9pack/__init__.py
qm9pack/qm9pack_getdata.py
qm9pack/qm9pack_utility.py
qm9pack/__pycache__/__init__.cpython-311.pyc
qm9pack/__pycache__/__init__.cpython-37.pyc
qm9pack/__pycache__/__init__.cpython-38.pyc
qm9pack/__pycache__/__init__.cpython-39.pyc
qm9pack/__pycache__/qm9pack_getdata.cpython-311.pyc
qm9pack/__pycache__/qm9pack_getdata.cpython-37.pyc
qm9pack/__pycache__/qm9pack_getdata.cpython-38.pyc
qm9pack/__pycache__/qm9pack_getdata.cpython-39.pyc
qm9pack/__pycache__/qm9pack_utility.cpython-311.pyc
qm9pack/__pycache__/qm9pack_utility.cpython-37.pyc
qm9pack/__pycache__/qm9pack_utility.cpython-38.pyc
qm9pack/data/qm9_part1.csv
qm9pack/data/qm9_part2.csv
qm9pack/data/qm9_part3.csv
qm9pack/data/qm9_polarizability.csv
qm9pack-1.0.3.dist-info/LICENSE
qm9pack-1.0.3.dist-info/METADATA
qm9pack-1.0.3.dist-info/WHEEL
qm9pack-1.0.3.dist-info/top_level.txt
qm9pack-1.0.3.dist-info/RECORD
