Metadata-Version: 2.1
Name: qm9pack
Version: 1.0.3
Summary: A python module for data-mining the qm9 database
Home-page: https://github.com/raghurama123/qm9pack
Author: Raghunathan Ramakrishnan
Author-email: raghu.rama.chem@gmail.com
License: MIT License
Platform: UNKNOWN
Requires-Dist: pandas
Requires-Dist: numpy
